{
    "map": "London.osm",
    "missions": [
        {
            "timestamp": "0",
            "name": "mission1",
            "stops": [
                {
                    "name": "Lidická"
                },
                {
                    "name": "Drobného"
                }
            ],
            "route": "Lužánky"
        },
        {
            "timestamp": "180",
            "name": "mission2",
            "stops": [
                {
                    "name": "Lidická"
                },
                {
                    "name": "Lidická"
                },
                {
                    "name": "Drobného"
                }
            ],
            "route": "Lužánky"
        }
    ]
}